<?xml version="1.0" encoding="utf-8"?>
<translations>
   <translation id="billing_payment_method_title" qtlid="139949">Moje sposoby płatności</translation>

   <translation id="billing_payment_method_load_error" qtlid="517277">Wystąpił błąd podczas ładowania Twoich metod płatności.</translation>

   <translation id="billing_payment_method_table_type" qtlid="176950">Typ płatności</translation>
   <translation id="billing_payment_method_table_label" qtlid="33862">Konto</translation>
   <translation id="billing_payment_method_table_expiration_date" qtlid="33010">Data wygasania</translation>
   <translation id="billing_payment_method_table_description" qtlid="9238">Opis</translation>
   <translation id="billing_payment_method_table_default" qtlid="224893">Domyślny sposób płatności</translation>
   <translation id="billing_payment_method_table_state" qtlid="492645">Status</translation>
   <translation id="billing_payment_method_table_3d_secure" qtlid="274876">3D Secure</translation>

   <translation id="billing_payment_method_table_top_add_method" qtlid="90253">Dodaj sposób płatności</translation>

   <translation id="billing_payment_method_autorenew_guide_help" qtlid="275688">Potrzebujesz pomocy w zakresie odnawiania usług?</translation>
   <translation id="billing_payment_method_autorenew_guide_help_link" qtlid="275688">Potrzebujesz pomocy w zakresie odnawiania usług?</translation>
   <translation id="billing_payment_method_bank_account_pending_validation" qtlid="325614">Dodałeś w panelu klienta konto bankowe. Czekamy na upoważnienie do obciążania rachunku. Należy przesłać je drogą pocztową.</translation>
   <translation id="billing_payment_method_bank_account_processing_delay" qtlid="325627">Twoje konto bankowe zostanie zatwierdzone w ciągu 24-48 godzin od uzyskania upoważnienia do obciążania rachunku.</translation>

   <translation id="billing_payment_method_table_action_download_procedure" qtlid="517290">Pobierz dokument i prześlij go do nas pocztą.</translation>
   <translation id="billing_payment_method_table_action_description_edit" qtlid="77274">Zmień opis</translation>
   <translation id="billing_payment_method_table_action_set_default" qtlid="517303">Ustaw tę metodę płatności jako domyślną</translation>
   <translation id="billing_payment_method_table_action_delete" qtlid="517316">Usuń tę metodę płatności</translation>

   <translation id="billing_payment_method_edit_error" qtlid="275247">Wystąpił błąd podczas modyfikowania opisu:</translation>
   <translation id="billing_payment_method_edit_success" qtlid="517329">Nastąpiła zmiana opisu Twojej metody płatności.</translation>

   <translation id="billing_payment_method_default_error" qtlid="517342">Wystąpił błąd podczas zmiany Twojej domyślnej metody płatności.</translation>
   <translation id="billing_payment_method_default_success" qtlid="517355">Twoja domyślna metoda płatności została zmieniona.</translation>

   <translation id="billing_payment_method_delete_error" qtlid="517368">Wystąpił błąd podczas usuwania metody płatności.</translation>
   <translation id="billing_payment_method_delete_success" qtlid="517381">Twoja metoda płatności została usunięta.</translation>
</translations>
