<?xml version="1.0" encoding="utf-8"?>
<translations>
   <translation id="billing_history_balance_title" qtlid="486724">Pay my balance</translation>
   <translation id="billing_history_balance_cancel" qtlid="37863">Cancel</translation>
   <translation id="billing_history_balance_explain" qtlid="486737">Your balance is currently {{ balance }}.</translation>
   <translation id="billing_history_balance_no_balance" qtlid="486750">No balance was found on your account. <a data-ui-sref="{{ backState }}">Click here</a> to return to the list of incoices.</translation>
   <translation id="billing_history_balance_choose_payment_method" qtlid="486763">Choose the payment method</translation>
   <translation id="billing_history_balance_add_payment_method" qtlid="486776">Add a payment method</translation>
   <translation id="billing_history_balance_no_payment_method" qtlid="486789">You have no valid payment method. <a data-ui-sref="{{ addPaymentMethodState }}">Add a valid payment method</a> before paying your balance.</translation>
   <translation id="billing_history_balance_payment_doing" qtlid="486802">A balance payment is already in progress. Wait for this payment to be made before paying a new balance.</translation>
   <translation id="billing_history_balance_payment_go_tracking" qtlid="486815">Go to the <a data-ui-sref="{{ trackState }}">payment tracking page</a> for more informations.</translation>

   <translation id="billing_history_balance_load_error" qtlid="486828">An error occurred while loading your balance.</translation>
   <translation id="billing_history_balance_pay_success" qtlid="486841">Your balance payment gas been taken in account. The payment will be effective in a few moments. Go to the <a data-ui-sref="{{ trackHref }}">payment tracking page</a> for more informations.</translation>
   <translation id="billing_history_balance_pay_error" qtlid="486854">An error occurred while paying your balance.</translation>

<!-- PAYMENT METHOD SUBTYPES -->
   <translation id="billing_history_balance_payment_method_subtype_american_express" qtlid="435959">American Express</translation>
   <translation id="billing_history_balance_payment_method_subtype_mastercard" qtlid="435985">Mastercard</translation>
   <translation id="billing_history_balance_payment_method_subtype_visa" qtlid="435972">Visa</translation>
</translations>
